devalog/__init__.py
devalog/client.py
devalog/core/__init__.py
devalog/core/api_error.py
devalog/core/client_wrapper.py
devalog/core/datetime_utils.py
devalog/core/file.py
devalog/core/force_multipart.py
devalog/core/http_client.py
devalog/core/http_response.py
devalog/core/jsonable_encoder.py
devalog/core/pydantic_utilities.py
devalog/core/query_encoder.py
devalog/core/remove_none_from_dict.py
devalog/core/request_options.py
devalog/core/serialization.py
devalog/imdb/__init__.py
devalog/imdb/client.py
devalog/imdb/errors/__init__.py
devalog/imdb/errors/movie_does_not_exist_error.py
devalog/imdb/raw_client.py
devalog/imdb/types/__init__.py
devalog/imdb/types/create_movie_request.py
devalog/imdb/types/movie.py
devalog/imdb/types/movie_id.py
devalog/py.typed
devalog/version.py
devin_package_new-0.0.2.dist-info/METADATA
devin_package_new-0.0.2.dist-info/WHEEL
devin_package_new-0.0.2.dist-info/RECORD
